yfmil3id2019/__init__.py
yfmil3id2019/_version.py
yfmil3id2019/algorithms/__init__.py
yfmil3id2019/algorithms/addition.py
yfmil3id2019/algorithms/multiplication.py
yfmil3id2019/ui/__init__.py
yfmil3id2019/ui/yfmil3id2019_test_app.py
yfmil3id2019/ui/yfmil3id2019_test_command_line.py
yfmil3id2019/ui/yfmil3id2019_train_app.py
yfmil3id2019/ui/yfmil3id2019_train_command_line.py
yunguanfu_mil3id2019-0.0.1.dist-info/LICENSE
yunguanfu_mil3id2019-0.0.1.dist-info/METADATA
yunguanfu_mil3id2019-0.0.1.dist-info/WHEEL
yunguanfu_mil3id2019-0.0.1.dist-info/entry_points.txt
yunguanfu_mil3id2019-0.0.1.dist-info/top_level.txt
yunguanfu_mil3id2019-0.0.1.dist-info/RECORD
