Metadata-Version: 2.1
Name: yunguanfu-mil3id2019
Version: 0.0.1
Summary: Implements Yunguan Fu's MIL3ID paper presented at MICCAI 2019
Home-page: https://weisslab.cs.ucl.ac.uk/WEISS/SoftwareRepositories/yunguanfu-mil3id2019
Author: Yunguan Fu
Author-email: yunguan.fu.18@ucl.ac.uk
License: BSD-3 license
Keywords: medical imaging
Platform: UNKNOWN
Classifier: Development Status :: 3 - Alpha
Classifier: Intended Audience :: Developers
Classifier: Intended Audience :: Healthcare Industry
Classifier: Intended Audience :: Information Technology
Classifier: Intended Audience :: Science/Research
Classifier: License :: OSI Approved :: BSD License
Classifier: Programming Language :: Python
Classifier: Programming Language :: Python :: 2
Classifier: Programming Language :: Python :: 3
Classifier: Topic :: Scientific/Engineering :: Information Analysis
Classifier: Topic :: Scientific/Engineering :: Medical Science Apps.
Requires-Dist: six (>=1.10)
Requires-Dist: numpy (>=1.11)
